CHANGES.txt
LICENSE.txt
MANIFEST.in
README.txt
setup.py
majorityjudgement/__init__.py
majorityjudgement/grading.py
majorityjudgement.egg-info/PKG-INFO
majorityjudgement.egg-info/SOURCES.txt
majorityjudgement.egg-info/dependency_links.txt
majorityjudgement.egg-info/top_level.txt