Metadata-Version: 1.0
Name: majorityjudgement
Version: 0.3.1
Summary: Implementation of majority judgement voting procedure
Home-page: https://github.com/DRMacIver/majority-judgement-python
Author: David R. MacIver
Author-email: david@drmaciver.com
License: LICENSE.txt
Platform: UNKNOWN
